{
	"11120": "二年制護理系",
	"11140": "四年制護理系",
	"11161": "護理系碩士班護研成人組",
	"11162": "護理系碩士班護研老人組",
	"11163": "護理系碩士班護研婦女組",
	"11164": "護理系碩士班護研精神組",
	"11165": "護理系碩士班護研社區組",
	"11166": "護理系碩士班護研兒童組",
	"11167": "護理系碩士班護研資訊組",
	"11168": "護理系碩士班護研成人專科組",
	"11169": "護理系中西醫結合護理碩士班",
	"11170": "護理系博士班",
	"11190": "護理系學士後學士班(學士後護理系)",
	"11230": "二年制進修部護理系(日間班)",
	"11330": "二年制進修部護理系(夜間班)",
	"11461": "護理系碩士在職專班護專成人組",
	"11462": "護理系碩士在職專班護專老人組",
	"11463": "護理系碩士在職專班護專婦女組",
	"11464": "護理系碩士在職專班護專精神組",
	"11465": "護理系碩士在職專班護專社區組",
	"11466": "護理系碩士在職專班護專兒童組",
	"11467": "護理系碩士在職專班護專資訊組",
	"11468": "護理系碩士在職專班護專成人專科組",
	"11860": "國際護理碩士班",
	"11870": "國際護理博士班",
	"13140": "四年制高齡健康照護系",
	"1C120": "二年制護理助產及婦女健康系",
	"1C160": "護理助產及婦女健康系護理助產碩士班",
	"1C330": "二年制進修部護理助產及婦女健康系",
	"1C860": "國際護理助產碩士班",
	"1D120": "二年制醫護教育暨數位學習系",
	"1D160": "醫護教育暨數位學習系碩士班",
	"20160": "健康科技學院碩士班",
	"21120": "二年制健康事業管理系",
	"21140": "四年制健康事業管理系",
	"21160": "健康事業管理系碩士班",
	"21330": "二年制進修部健康事業管理系",
	"21460": "健康事業管理系碩士在職專班",
	"22140": "四年制資訊管理系",
	"22160": "資訊管理系碩士班",
	"23140": "四年制休閒產業與健康促進系",
	"23160": "休閒產業與健康促進系旅遊健康碩士班",
	"23460": "休閒產業與健康促進系碩士在職專班",
	"24120": "二年制長期照護系",
	"24150": "長期照護系學士後多元專長培力課程專班",
	"24160": "長期照護系碩士班",
	"25140": "四年制語言治療與聽力學系",
	"25161": "語言治療與聽力學系碩士班語言治療組",
	"25162": "語言治療與聽力學系碩士班聽力組",
	"25460": "語言治療與聽力學系在職專班",
	"26860": "國際健康科技碩士學位學程國際生碩士班",
	"30860": "國際運動科學外國學生專班",
	"31120": "二年制嬰幼兒保育系",
	"31140": "四年制嬰幼兒保育系",
	"31160": "嬰幼兒保育系碩士班",
	"31860": "國際蒙特梭利碩士專班",
	"32140": "四年制運動保健系",
	"32160": "運動保健系碩士班",
	"32460": "運動保健系碩士在職專班",
	"33140": "四年制生死與健康心理諮商系",
	"33161": "生死與健康心理諮商系碩士班生死學組",
	"33162": "生死與健康心理諮商系碩士班諮商心理組",
	"42140": "智慧健康科技技優專班"
}
